simulacrum/__init__.py
simulacrum/_errors.py
simulacrum/api.py
simulacrum/client.py
simulacrum/config.py
simulacrum/exceptions.py
simulacrum/models.py
simulacrum_sdk-0.2.5.dist-info/licenses/LICENSE
simulacrum_sdk-0.2.5.dist-info/METADATA
simulacrum_sdk-0.2.5.dist-info/WHEEL
simulacrum_sdk-0.2.5.dist-info/top_level.txt
simulacrum_sdk-0.2.5.dist-info/RECORD
