Metadata-Version: 2.4
Name: simulacrum-sdk
Version: 0.2.5
Summary: Official Python SDK for accessing the Simulacrum API.
Author-email: "Simulacrum, Inc." <support@smlcrm.com>
License-Expression: MIT
Project-URL: Homepage, https://smlcrm-tempo-api.readme.io/reference
Project-URL: Repository, https://github.com/Smlcrm/simulacrum-sdk
Project-URL: Issues, https://github.com/Smlcrm/simulacrum-sdk/issues
Keywords: Simulacrum,time-series,forecasting,sdk
Classifier: Development Status :: 3 - Alpha
Classifier: Intended Audience :: Developers
Classifier: Operating System :: OS Independent
Classifier: Programming Language :: Python :: 3
Classifier: Programming Language :: Python :: 3 :: Only
Classifier: Programming Language :: Python :: 3.8
Classifier: Programming Language :: Python :: 3.9
Classifier: Programming Language :: Python :: 3.10
Classifier: Programming Language :: Python :: 3.11
Classifier: Programming Language :: Python :: 3.12
Classifier: Topic :: Scientific/Engineering :: Artificial Intelligence
Requires-Python: >=3.8
License-File: LICENSE
Requires-Dist: httpx<1,>=0.27
Requires-Dist: pydantic<3,>=2.0
Requires-Dist: numpy>=1.24
Provides-Extra: dev
Requires-Dist: pytest>=8.0; extra == "dev"
Requires-Dist: build>=1.2; extra == "dev"
Requires-Dist: twine>=5.0; extra == "dev"
Dynamic: license-file
